py3shark-0.4.0.dist-info/DESCRIPTION.rst
py3shark-0.4.0.dist-info/METADATA
py3shark-0.4.0.dist-info/RECORD
py3shark-0.4.0.dist-info/WHEEL
py3shark-0.4.0.dist-info/metadata.json
py3shark-0.4.0.dist-info/top_level.txt
pyshark/__init__.py
pyshark/config.ini
pyshark/config.py
pyshark/capture/__init__.py
pyshark/capture/capture.py
pyshark/capture/file_capture.py
pyshark/capture/inmem_capture.py
pyshark/capture/live_capture.py
pyshark/capture/live_ring_capture.py
pyshark/capture/pipe_capture.py
pyshark/capture/remote_capture.py
pyshark/packet/__init__.py
pyshark/packet/common.py
pyshark/packet/consts.py
pyshark/packet/fields.py
pyshark/packet/layer.py
pyshark/packet/packet.py
pyshark/packet/packet_summary.py
pyshark/tshark/__init__.py
pyshark/tshark/tshark.py
pyshark/tshark/tshark_json.py
pyshark/tshark/tshark_xml.py
