Metadata-Version: 2.0
Name: py3shark
Version: 0.4.0
Summary: Python wrapper for tshark, a fork for pyshark support Python3.5+
Home-page: https://github.com/laixintao/py3shark
Author: KimiNewt
Author-email: UNKNOWN
License: UNKNOWN
Keywords: wireshark capture packets parsing packet
Platform: UNKNOWN
Classifier: License :: OSI Approved :: MIT License
Classifier: Programming Language :: Python :: 3.5
Requires-Dist: lxml
Requires-Dist: py
Requires-Dist: logbook
